rplus_graphdb/__init__.py
rplus_graphdb/connection/__init__.py
rplus_graphdb/connection/graph_connection.py
rplus_graphdb/graph.py
rplus_graphdb/interface/__init__.py
rplus_graphdb/interface/connection_iface.py
rplus_graphdb/interface/custom_query_iface.py
rplus_graphdb/interface/node_create_constraint_iface.py
rplus_graphdb/interface/node_create_iface.py
rplus_graphdb/interface/node_create_index_iface.py
rplus_graphdb/interface/node_delete_iface.py
rplus_graphdb/interface/node_search_iface.py
rplus_graphdb/interface/node_update_iface.py
rplus_graphdb/interface/rel_create_iface.py
rplus_graphdb/interface/rel_delete_iface.py
rplus_graphdb/interface/rel_update_iface.py
rplus_graphdb/schema/__init__.py
rplus_graphdb/schema/node.py
rplus_graphdb/schema/relationship.py
rplus_graphdb/utils/__init__.py
rplus_graphdb/utils/constant.py
rplus_graphdb/utils/execution_time.py
rplus_graphdb/utils/util.py
rplus_graphdb_module-0.0.3.dist-info/WHEEL
rplus_graphdb_module-0.0.3.dist-info/METADATA
rplus_graphdb_module-0.0.3.dist-info/RECORD
